logpy/__init__.py
logpy/log.py
logpy/py.typed
pylogpy-1.5.2.dist-info/METADATA
pylogpy-1.5.2.dist-info/WHEEL
pylogpy-1.5.2.dist-info/licenses/LICENSE
pylogpy-1.5.2.dist-info/RECORD
