Metadata-Version: 2.4
Name: pylogpy
Version: 1.5.2
Summary: Production-ready Python logging package with color-coded output, rotating file logs, and optional email alerts
License: MIT
License-File: LICENSE
Keywords: logging,logger,color,ansi,structured-logging,email-alerts
Author: bek42
Author-email: bharani.nitturi@gmail.com
Maintainer: bek42
Maintainer-email: bharani.nitturi@gmail.com
Requires-Python: >=3.12,<4.0
Classifier: Development Status :: 5 - Production/Stable
Classifier: Environment :: Console
Classifier: Intended Audience :: Developers
Classifier: License :: OSI Approved :: MIT License
Classifier: Operating System :: Microsoft :: Windows
Classifier: Operating System :: POSIX :: Linux
Classifier: Programming Language :: Python :: 3
Classifier: Programming Language :: Python :: 3.12
Classifier: Programming Language :: Python :: 3.13
Classifier: Programming Language :: Python :: 3.14
Classifier: Topic :: Software Development :: Libraries :: Python Modules
Classifier: Topic :: System :: Logging
Provides-Extra: azure-keyvault
Requires-Dist: python-dotenv (>=1.0.1,<2.0.0)
Project-URL: Documentation, https://github.com/bek42/logpy#readme
Project-URL: Homepage, https://github.com/bek42/logpy
Project-URL: Repository, https://github.com/bek42/logpy
